meshparty/__init__.py
meshparty/iterator.py
meshparty/mesh_filters.py
meshparty/mesh_skel_utils.py
meshparty/meshlabserver.py
meshparty/ray_tracing.py
meshparty/skeleton.py
meshparty/skeleton_io.py
meshparty/skeleton_utils.py
meshparty/skeletonize.py
meshparty/spatial_annotations.py
meshparty/trimesh_io.py
meshparty/trimesh_repair.py
meshparty/trimesh_vtk.py
meshparty/utils.py
meshparty/utils_io.py
meshparty/meshwork/__init__.py
meshparty/meshwork/algorithms.py
meshparty/meshwork/meshwork.md
meshparty/meshwork/meshwork.py
meshparty/meshwork/meshwork_io.py
meshparty/meshwork/utils.py
meshparty/skeleton_quality/__init__.py
meshparty/skeleton_quality/multicut.py
meshparty/skeleton_quality/skeleton_quality.py
meshparty-2.0.3.dist-info/METADATA
meshparty-2.0.3.dist-info/WHEEL
meshparty-2.0.3.dist-info/licenses/LICENSE
meshparty-2.0.3.dist-info/RECORD
