Metadata-Version: 2.4
Name: meshparty
Version: 2.0.3
Summary: a service to work with meshes
Project-URL: Homepage, https://github.com/CAVEconnectome/MeshParty
Project-URL: Bug Tracker, https://github.com/CAVEconnectome/MeshParty/issues
Author-email: Sven Dorkenwald <svenmd@princeton.edu>, Forrest Collman <forrestc@alleninstitute.org>, Casey Schneider-Mizell <caseys@alleninstitute.org>
License: MIT
License-File: LICENSE
Classifier: License :: OSI Approved :: MIT License
Classifier: Operating System :: OS Independent
Classifier: Programming Language :: Python :: 3
Requires-Python: >=3.10
Requires-Dist: blosc>=1.11.2
Requires-Dist: cloud-volume>=1.16.0
Requires-Dist: h5py
Requires-Dist: multiwrapper
Requires-Dist: networkx
Requires-Dist: numpy>=2.0.0
Requires-Dist: orjson>=3.0.0
Requires-Dist: pandas>=2.0.0
Requires-Dist: scikit-learn
Requires-Dist: scipy>=1.3.0
Requires-Dist: tables>=3.0.0
Requires-Dist: trimesh[easy]>=4.0.0
Provides-Extra: repair
Requires-Dist: caveclient>=4.0.0; extra == 'repair'
Provides-Extra: test
Requires-Dist: pytest; extra == 'test'
Requires-Dist: pytest-cov; extra == 'test'
Requires-Dist: pytest-mock; extra == 'test'
Provides-Extra: viz
Requires-Dist: vtk; extra == 'viz'
